print_mxmul_pkg/__init__.py
print_mxmul_pkg/print_mxmul.py
print_mxmul_pkg-0.1.0.dist-info/LICENSE
print_mxmul_pkg-0.1.0.dist-info/METADATA
print_mxmul_pkg-0.1.0.dist-info/WHEEL
print_mxmul_pkg-0.1.0.dist-info/top_level.txt
print_mxmul_pkg-0.1.0.dist-info/RECORD
