Metadata-Version: 2.1
Name: print-mxmul-pkg
Version: 0.1.0
Summary: An example for teaching how to publish a Python package
Home-page: https://github.com/pypa/sampleproject
Author: printwork
Author-email: printwork@126.com
License: UNKNOWN
Platform: UNKNOWN
Classifier: Programming Language :: Python :: 3
Classifier: License :: OSI Approved :: MIT License
Classifier: Operating System :: OS Independent
License-File: LICENSE
